Perceptron/__init__.py
Perceptron/perceptron.py
Perceptron_pypi_Manirathinam21-0.0.1.dist-info/LICENSE
Perceptron_pypi_Manirathinam21-0.0.1.dist-info/METADATA
Perceptron_pypi_Manirathinam21-0.0.1.dist-info/WHEEL
Perceptron_pypi_Manirathinam21-0.0.1.dist-info/top_level.txt
Perceptron_pypi_Manirathinam21-0.0.1.dist-info/RECORD
