Metadata-Version: 2.1
Name: Perceptron-pypi-Manirathinam21
Version: 0.0.1
Summary: it's an implementatiom of perceptron
Home-page: https://github.com/Manirathinam21/Perceptron_pypi
Author: USER_NAME
Author-email: manirathinam21@gmail.com
License: UNKNOWN
Project-URL: Bug Tracker, https://github.com/Manirathinam21/Perceptron_pypi/issues
Platform: UNKNOWN
Classifier: Programming Language :: Python :: 3
Classifier: License :: OSI Approved :: MIT License
Classifier: Operating System :: OS Independent
Requires-Python: >=3.7
License-File: LICENSE
Requires-Dist: numpy
Requires-Dist: tqdm
